devmathimpro/__init__.py
devmathimpro/math_utils.py
devmathimpro-0.1.dist-info/METADATA
devmathimpro-0.1.dist-info/WHEEL
devmathimpro-0.1.dist-info/top_level.txt
devmathimpro-0.1.dist-info/RECORD
