Metadata-Version: 2.1
Name: devmathimpro
Version: 0.1
Summary: Простая библиотека для математических операций
Author: improve
Author-email: vlasav227@mail.ru
Classifier: Programming Language :: Python :: 3
Classifier: License :: OSI Approved :: MIT License
Classifier: Operating System :: OS Independent
Requires-Python: >=3.6
